excel_reporting/__init__.py
excel_reporting/report.jar
excel_reporting/report_gen.py
excel_reporting/demo/__init__.py
excel_reporting/demo/actions.py
excel_reporting/demo/app_meta.py
excel_reporting/demo/controller.py
excel_reporting/demo/example-template.xls
excel_reporting/demo/models.py
excel_reporting/report_lib/json_simple-1.1.jar
excel_reporting/report_lib/poi-3.7-20101029.jar
excel_reporting/report_lib/poi-ooxml-3.7-20101029.jar
excel_reporting/report_src/Report.java
excel_reporting/report_src/build.sh
excel_reporting/report_src/manifest.mf
m3_excel_reporting-2.5.0.dist-info/licenses/LICENSE
m3_excel_reporting-2.5.0.dist-info/METADATA
m3_excel_reporting-2.5.0.dist-info/WHEEL
m3_excel_reporting-2.5.0.dist-info/dependency_links.txt
m3_excel_reporting-2.5.0.dist-info/top_level.txt
m3_excel_reporting-2.5.0.dist-info/RECORD
