Metadata-Version: 2.4
Name: m3-excel-reporting
Version: 2.5.0
Home-page: https://bitbucket.org/barsgroup/excel-reporting
Author: BARS Group
Author-email: bars@bars-open.ru
License: MIT
Classifier: Intended Audience :: Developers
Classifier: Environment :: Web Environment
Classifier: Natural Language :: Russian
Classifier: Natural Language :: English
Classifier: Operating System :: OS Independent
Classifier: Programming Language :: Python
Classifier: License :: OSI Approved :: MIT License
Classifier: Development Status :: 5 - Production/Stable
License-File: LICENSE
Requires-Dist: m3_django_compatibility<2,>=1.12.0
Requires-Dist: django<5.0,>=1.4
Requires-Dist: m3-builder<=1.2.0,>=1.0.1
Dynamic: author
Dynamic: author-email
Dynamic: classifier
Dynamic: home-page
Dynamic: license
Dynamic: license-file
Dynamic: requires-dist
